almapipy/__init__.py
almapipy/acquisitions.py
almapipy/analytics.py
almapipy/bibs.py
almapipy/client.py
almapipy/conf.py
almapipy/courses.py
almapipy/electronic.py
almapipy/partners.py
almapipy/primo.py
almapipy/task_lists.py
almapipy/users.py
almapipy/utils.py
almapipy-1.0.3.dist-info/METADATA
almapipy-1.0.3.dist-info/WHEEL
almapipy-1.0.3.dist-info/top_level.txt
almapipy-1.0.3.dist-info/RECORD
