Metadata-Version: 2.1
Name: almapipy
Version: 1.0.3
Summary: Python requests wrapper for the Ex Libris Alma API
Home-page: https://github.com/UCDavisLibrary/almapipy
Author: Steve Pelkey
Author-email: spelkey@ucdavis.edu
License: MIT
Keywords: alma exlibris exlibrisgroup api bibliographic
Platform: UNKNOWN
Classifier: Intended Audience :: Developers
Classifier: Intended Audience :: Education
Classifier: Intended Audience :: Science/Research
Classifier: License :: OSI Approved :: MIT License
Classifier: Natural Language :: English
Classifier: Operating System :: OS Independent
Classifier: Programming Language :: Python
Classifier: Topic :: Software Development :: Libraries :: Python Modules
Classifier: Programming Language :: Python :: 3
Requires-Python: >=3.0
Requires-Dist: requests
